jtech_mcp_executor/__init__.py
jtech_mcp_executor/client.py
jtech_mcp_executor/config.py
jtech_mcp_executor/logging.py
jtech_mcp_executor/session.py
jtech_mcp_executor/adapters/__init__.py
jtech_mcp_executor/adapters/base.py
jtech_mcp_executor/adapters/langchain_adapter.py
jtech_mcp_executor/agents/__init__.py
jtech_mcp_executor/agents/base.py
jtech_mcp_executor/agents/mcpagent.py
jtech_mcp_executor/agents/prompts/system_prompt_builder.py
jtech_mcp_executor/agents/prompts/templates.py
jtech_mcp_executor/connectors/__init__.py
jtech_mcp_executor/connectors/base.py
jtech_mcp_executor/connectors/http.py
jtech_mcp_executor/connectors/stdio.py
jtech_mcp_executor/connectors/websocket.py
jtech_mcp_executor/managers/__init__.py
jtech_mcp_executor/managers/server_manager.py
jtech_mcp_executor/managers/tools/__init__.py
jtech_mcp_executor/managers/tools/base_tool.py
jtech_mcp_executor/managers/tools/connect_server.py
jtech_mcp_executor/managers/tools/disconnect_server.py
jtech_mcp_executor/managers/tools/get_active_server.py
jtech_mcp_executor/managers/tools/list_servers_tool.py
jtech_mcp_executor/managers/tools/search_tools.py
jtech_mcp_executor/managers/tools/use_tool.py
jtech_mcp_executor/orchestration/__init__.py
jtech_mcp_executor/orchestration/aggregator.py
jtech_mcp_executor/orchestration/crew.py
jtech_mcp_executor/orchestration/memory.py
jtech_mcp_executor/orchestration/task.py
jtech_mcp_executor/orchestration/workflow.py
jtech_mcp_executor/task_managers/__init__.py
jtech_mcp_executor/task_managers/base.py
jtech_mcp_executor/task_managers/sse.py
jtech_mcp_executor/task_managers/stdio.py
jtech_mcp_executor/task_managers/websocket.py
jtech_mcp_executor-1.0.3.dist-info/METADATA
jtech_mcp_executor-1.0.3.dist-info/WHEEL
jtech_mcp_executor-1.0.3.dist-info/licenses/LICENSE
jtech_mcp_executor-1.0.3.dist-info/RECORD
