Metadata-Version: 2.4
Name: jtech_mcp_executor
Version: 1.0.3
Summary: MCP Library for LLMs
Author-email: Angelo Vicente Filho <angelo.vicente@veolia.com>
License-File: LICENSE
Requires-Python: <4.0,>=3.12
Requires-Dist: aiohttp>=3.9.0
Requires-Dist: jsonschema-pydantic>=0.1.0
Requires-Dist: langchain-community>=0.0.10
Requires-Dist: langchain>=0.1.0
Requires-Dist: mcp>=1.5.0
Requires-Dist: pydantic>=2.0.0
Requires-Dist: python-dotenv>=1.0.0
Requires-Dist: typing-extensions>=4.8.0
Requires-Dist: websockets>=12.0
Provides-Extra: anthropic
Requires-Dist: anthropic>=0.15.0; extra == 'anthropic'
Provides-Extra: dev
Requires-Dist: black>=23.9.0; extra == 'dev'
Requires-Dist: isort>=5.12.0; extra == 'dev'
Requires-Dist: mypy>=1.5.0; extra == 'dev'
Requires-Dist: pytest-asyncio>=0.21.0; extra == 'dev'
Requires-Dist: pytest-cov>=4.1.0; extra == 'dev'
Requires-Dist: pytest>=7.4.0; extra == 'dev'
Requires-Dist: ruff>=0.1.0; extra == 'dev'
Provides-Extra: openai
Requires-Dist: openai>=1.10.0; extra == 'openai'
Provides-Extra: search
Requires-Dist: fastembed>=0.0.1; extra == 'search'
